odoo/addons/sale_line_returned_qty_mrp/README.rst
odoo/addons/sale_line_returned_qty_mrp/__init__.py
odoo/addons/sale_line_returned_qty_mrp/__manifest__.py
odoo/addons/sale_line_returned_qty_mrp/i18n/sale_line_returned_qty_mrp.pot
odoo/addons/sale_line_returned_qty_mrp/models/__init__.py
odoo/addons/sale_line_returned_qty_mrp/models/sale_order_line.py
odoo/addons/sale_line_returned_qty_mrp/readme/CONTRIBUTORS.rst
odoo/addons/sale_line_returned_qty_mrp/readme/DESCRIPTION.rst
odoo/addons/sale_line_returned_qty_mrp/static/description/icon.png
odoo/addons/sale_line_returned_qty_mrp/static/description/index.html
odoo/addons/sale_line_returned_qty_mrp/tests/__init__.py
odoo/addons/sale_line_returned_qty_mrp/tests/test_sale_line_returned_qty_mrp.py
odoo13_addon_sale_line_returned_qty_mrp-13.0.1.0.1.dist-info/METADATA
odoo13_addon_sale_line_returned_qty_mrp-13.0.1.0.1.dist-info/WHEEL
odoo13_addon_sale_line_returned_qty_mrp-13.0.1.0.1.dist-info/top_level.txt
odoo13_addon_sale_line_returned_qty_mrp-13.0.1.0.1.dist-info/RECORD
